gkraken/__init__.py
gkraken/app.py
gkraken/conf.py
gkraken/di.py
gkraken/interactor.py
gkraken/main.py
gkraken/model.py
gkraken/repository.py
gkraken/data/60-gkraken.rules
gkraken/data/edit_speed_profile.glade
gkraken/data/gkraken-symbolic.svg
gkraken/data/gkraken.svg
gkraken/data/gkraken.svg-path826-6-4294967105.png
gkraken/data/main.glade
gkraken/data/preferences.glade
gkraken/presenter/__init__.py
gkraken/presenter/edit_speed_profile.py
gkraken/presenter/main.py
gkraken/presenter/preferences.py
gkraken/util/__init__.py
gkraken/util/concurrency.py
gkraken/util/desktop_entry.py
gkraken/util/log.py
gkraken/util/path.py
gkraken/util/udev.py
gkraken/util/view.py
gkraken/util/desktop/__init__.py
gkraken/util/desktop/desktop_parser.py
gkraken/view/__init__.py
gkraken/view/edit_speed_profile.py
gkraken/view/main.py
gkraken/view/preferences.py
gkraken-0.12.2.dist-info/COPYING.txt
gkraken-0.12.2.dist-info/METADATA
gkraken-0.12.2.dist-info/WHEEL
gkraken-0.12.2.dist-info/entry_points.txt
gkraken-0.12.2.dist-info/top_level.txt
gkraken-0.12.2.dist-info/RECORD
