Metadata-Version: 2.1
Name: gkraken
Version: 0.12.2
Summary: GUI to control cooling and lighting of NZXT Kraken X (X42, X52, X62 or X72) pumps
Home-page: https://gitlab.com/leinardi/gkraken
Author: Roberto Leinardi
Author-email: roberto@leinardi.com
License: UNKNOWN
Project-URL: Source, https://gitlab.com/leinardi/gkraken
Project-URL: Tracker, https://gitlab.com/leinardi/gkraken/issues
Project-URL: Changelog, https://gitlab.com/leinardi/gkraken/blob/0.12.2/CHANGELOG.md
Project-URL: Documentation, https://gitlab.com/leinardi/gkraken/blob/0.12.2/README.md
Keywords: nzxt kraken
Platform: UNKNOWN
Classifier: Development Status :: 3 - Alpha
Classifier: Environment :: X11 Applications :: GTK
Classifier: Intended Audience :: End Users/Desktop
Classifier: License :: OSI Approved :: GNU General Public License v3 or later (GPLv3+)
Classifier: Operating System :: POSIX :: Linux
Classifier: Programming Language :: Python :: 3.6
Classifier: Topic :: Desktop Environment :: Gnome
Classifier: Topic :: System :: Hardware
Classifier: Topic :: System :: Monitoring
Classifier: Topic :: Utilities
Requires-Python: ~=3.6
Requires-Dist: injector (==0.14.1)
Requires-Dist: liquidctl (==1.0.0)
Requires-Dist: matplotlib (==3.0.0)
Requires-Dist: peewee (==3.7.1)
Requires-Dist: pygobject
Requires-Dist: pyxdg
Requires-Dist: requests
Requires-Dist: rx (==1.6.1)
